{
   "taix_items":[
      {
         "name":"\u5b9e\u65f6\u8ba2\u5355",
         "items":[
            {
               "name":"\u547c\u53eb\u91cf",
               "id":"monitor_taxi_realtime_order_call_num",
               "title":"\u6309\u7167\u8ba2\u5355\u9996\u6b21\u547c\u53eb\u65f6\u95f4\u7edf\u8ba1\u3002\u5f53\u524d\u63d2\u5165type=0\u7684\u8ba2\u5355\u6570\u3002datasource=order_b",
               "druidDataSource":"m2_dc_db_recentorder_fmt_001"
            },
            {
               "name":"\u6210\u4ea4\u91cf",
               "id":"monitor_taxi_realtime_order_succ_num",
               "title":"\u6309\u7167\u8ba2\u5355\u547c\u53eb\u65f6\u95f4\u7edf\u8ba1\u3002\u6210\u4ea4\u91cf\u4f7f\u7528\u5f53\u524d\u65f6\u523b\u7684\u5e94\u7b54\u91cf(type=0\uff0cstatus\u4ece0\u53d8\u4e3a1,2,3,4,9,11)-\u5e94\u7b54\u540e\u53d6\u6d88\u91cf(status\u53d8\u4e3a4,9)\u3002\uff08\u6570\u636e\u8bef\u5dee\u53ef\u4ee5\u63a5\u53d7\uff09\u3002 datasource=order_b",
               "druidDataSource":"m2_dc_db_recentorder_fmt_001"
            },
            {
               "name":"\u5e94\u7b54\u7387",
               "id":"monitor_taxi_realtime_order_succ_rate",
               "title":"\u5e94\u7b54\u91cf\/\u547c\u53eb\u91cf\u3002\u65f6\u523bs\u7684\u5e94\u7b54\u7387 = \u65f6\u523bs\u5206\u949f\u547c\u53eb\u7684\u5230\u5f53\u524d\u65f6\u523b\u88ab\u5e94\u7b54\u6570 \/ \u65f6\u523bs\u5206\u949f\u547c\u53eb\u8ba2\u5355\u6570\u3002\u5982\u679c\u65f6\u523bs\u548c\u5f53\u524d\u65f6\u523b\u63a5\u8fd1\u7684\u8bdd\uff0c\u5b9e\u65f6\u5e94\u7b54\u7387\u5c31\u53ef\u80fd\u504f\u4f4e\u3002",
               "warn":0
            },
            {
               "name":"\u5b9e\u65f6\u5e73\u53f0\u5956\u52b1\u8ba2\u5355\u91cf",
               "id":"monitor_taxi_realtime_order_bonus_num",
               "title":"\u6309\u7167\u5956\u52b1\u65f6\u95f4\uff0c\u7edf\u8ba1\u5e73\u53f0\u5956\u52b1\u8ba2\u5355\u91cf\u3002type=0 && bonus\u53d8\u4e3a>0 && \u8ba2\u5355\u72b6\u6001 in(1,2,3,11)\u3002\u6570\u636e\u6e90\u4e3aorder_b"
            },
            {
               "name":"\u5b9e\u65f6\u5e73\u53f0\u5956\u52b1\u91d1\u989d",
               "id":"monitor_taxi_realtime_order_bonus_money",
               "title":"\u6309\u7167\u5956\u52b1\u65f6\u95f4\uff0c\u7edf\u8ba1\u5e73\u53f0\u5956\u52b1\u91d1\u989d\u3002type=0 && bonus\u53d8\u4e3a>0 and \u8ba2\u5355\u72b6\u6001 in(1,2,3,11)\u3002\u6570\u636e\u6e90\u4e3aorder_b"
            },
            {
               "name":"\u64ad\u5355\u91cf",
               "id":"monitor_taxi_realtime_order_broadcast_num",
               "title":"\u6570\u636e\u6765\u6e90\u4e8e\u65e5\u5fd7\u3002\u6309\u7167\u64ad\u5355\u65f6\u95f4\u7edf\u8ba1\u3002\u6570\u636e\u6e90flume_taxi_broadcast\u3002"
            },
            {
               "name":"\u5e94\u7b54\u91cf",
               "id":"monitor_taxi_realtime_order_answer_num",
               "title":"\u6309\u7167\u547c\u53eb\u65f6\u95f4\u7edf\u8ba1\u3002type=0 and status\u4ece0\u53d8\u4e3a(1,2,3,4,9,11)\u3002\u6570\u636e\u6e90order_b"
            },
            {
               "name":"\u62a2\u5355\u91cf",
               "id":"monitor_taxi_realtime_order_strive_num",
               "title":"metric_key=striverdistance and type=0. \u6570\u636e\u6e90flume_dache_api"
            },
            {
               "name":"\u542c\u5355\u62a2\u5355\u7387",
               "id":"monitor_taxi_realtime_order_strive_rate",
               "title":"\u62a2\u5355\u91cf\/\u64ad\u5355\u91cf",
               "warn":0
            },
            {
               "name":"\u5e73\u5747\u6210\u4ea4\u8ddd\u79bb",
               "id":"monitor_taxi_realtime_order_avg_deal_distance",
               "title":"\u5e73\u5747\u6210\u4ea4\u8ddd\u79bb",
               "warn":0
            },
            {
               "name":"\u5b9e\u65f6str\u503c",
               "id":"monitor_taxi_realtime_order_str",
               "title":"type=0. dataSource=flume_strategy_service"
            },
            {
               "name":"\u62a2\u5355\u56de\u8c03\u91cf",
               "id":"monitor_taxi_strive_result_num",
               "title":"metric_key=taxi_strive_result. \u6570\u636e\u6e90flume_dache_api"
            }
         ]
      },
      {
         "name":"\u5b9e\u65f6\u8ba2\u5355\u53d6\u6d88\u7387",
         "items":[
            {
               "name":"\u4e58\u5ba2\u5e94\u7b54\u540e\u53d6\u6d88\u7387",
               "id":"monitor_taxi_passenger_after_deal_cancel_rate",
               "title":"\u4e58\u5ba2\u7ec8\u6b62\u8ba2\u5355\u91cf\uff08status\u53d8\u4e3a9\uff09\/\u5b9e\u65f6\u8ba2\u5355\u5e94\u7b54\u91cf",
               "warn":0
            },
            {
               "name":"\u53f8\u673a\u5e94\u7b54\u540e\u53d6\u6d88\u7387",
               "id":"monitor_taxi_driver_after_deal_cancel_rate",
               "title":"\u53f8\u673a\u7ec8\u6b62\u8ba2\u5355\u91cf\uff08status\u53d8\u4e3a4\uff09\/\u5b9e\u65f6\u8ba2\u5355\u5e94\u7b54\u91cf",
               "warn":0
            },
            {
               "name":"\u672a\u5e94\u7b54\u53d6\u6d88\u7387",
               "id":"monitor_taxi_no_deal_cancel_rate",
               "title":"\u4e58\u5ba2\u53d6\u6d88\u8ba2\u5355(status\u53d8\u4e3a7)\/\u5b9e\u65f6\u8ba2\u5355\u547c\u53eb\u91cf",
               "warn":0
            },
            {
               "name":"\u8ba2\u5355\u5e94\u7b54\u540e\u4e58\u5ba2\u53d6\u6d88\u91cf",
               "id":"monitor_taxi_passenger_after_deal_cancel_num",
               "title":"type=0 && status\u53d8\u4e3a9\u3002\u6570\u636e\u6e90:order_b"
            },
            {
               "name":"\u8ba2\u5355\u5e94\u7b54\u540e\u53f8\u673a\u53d6\u6d88\u91cf",
               "id":"monitor_taxi_driver_after_deal_cancel_bum",
               "title":"type=0 && status\u53d8\u4e3a4.\u6570\u636e\u6e90\u4e3a\uff1aorder_b"
            },
            {
               "name":"\u8ba2\u5355\u5e94\u7b54\u524d\u4e58\u5ba2\u53d6\u6d88\u91cf",
               "id":"monitor_taxi_no_deal_cancel_num",
               "title":"type=0 && status\u53d8\u4e3a7.\u6570\u636e\u6e90\u4e3a\uff1aorder_b"
            }
         ]
      },
      {
         "name":"\u5feb\u7684\u5bfc\u6d41\u5b9e\u65f6\u8ba2\u5355",
         "items":[
            {
               "name":"\u547c\u53eb\u91cf",
               "id":"monitor_taxi_kuaidi_realtime_order_call_num",
               "title":"\u6309\u7167\u547c\u53eb\u65f6\u95f4\u7edf\u8ba1.type=0 && \u65b0\u63d2\u5165\u7684kuaidi_oid \uff01=0\u7684\u8ba2\u5355 .dataSource=order_b"
            },
            {
               "name":"\u6210\u4ea4\u91cf",
               "id":"monitor_taxi_kuaidi_realtime_order_succ_num",
               "title":"\u6309\u7167\u547c\u53eb\u65f6\u95f4\u7edf\u8ba1\u3002type=0 && \u8ba2\u5355\u72b6\u6001status\u4ece0\u53d8\u4e3a1,2,3,11\u3002\u6570\u636e\u6e90\uff1aorder_b"
            },
            {
               "name":"\u5e94\u7b54\u7387",
               "id":"monitor_taxi_kuaidi_realtime_order_succ_rate",
               "title":"\u6210\u4ea4\u91cf\/\u547c\u53eb\u91cf.\u65f6\u523bs\u7684\u5e94\u7b54\u7387 = \u65f6\u523bs\u5206\u949f\u547c\u53eb\u7684\u5230\u5f53\u524d\u65f6\u523b\u88ab\u5e94\u7b54\u6570 \/ \u65f6\u523bs\u5206\u949f\u547c\u53eb\u8ba2\u5355\u6570\u3002\u5982\u679c\u65f6\u523bs\u548c\u5f53\u524d\u65f6\u523b\u63a5\u8fd1\u7684\u8bdd\uff0c\u5b9e\u65f6\u5e94\u7b54\u7387\u5c31\u53ef\u80fd\u504f\u4f4e\u3002",
               "warn":0
            }
         ]
      },
      {
         "name":"\u9884\u7ea6\u8ba2\u5355",
         "items":[
            {
               "name":"\u547c\u53eb\u91cf",
               "id":"monitor_taxi_reservation_order_call_num",
               "title":"\u6309\u547c\u53eb\u65f6\u95f4\u7edf\u8ba1\u3002\u65b0\u63d2\u5165\u7684type=1\u7684\u8ba2\u5355.dataSource=order_b"
            },
            {
               "name":"\u6210\u4ea4\u91cf",
               "id":"monitor_taxi_reservation_order_succ_num",
               "title":"\u6309\u547c\u53eb\u65f6\u95f4\u7edf\u8ba1\u3002type=1 && \u8ba2\u5355\u72b6\u6001\u4ece0\u53d8\u4e3a1,2,3,11. dataSource=order_b"
            },
            {
               "name":"\u5e94\u7b54\u7387",
               "id":"monitor_taxi_reservation_order_succ_rate",
               "title":"\u6210\u4ea4\u91cf\/\u547c\u53eb\u91cf.\u65f6\u523bs\u7684\u5e94\u7b54\u7387 = \u65f6\u523bs\u5206\u949f\u547c\u53eb\u7684\u5230\u5f53\u524d\u65f6\u523b\u88ab\u5e94\u7b54\u6570 \/ \u65f6\u523bs\u5206\u949f\u547c\u53eb\u8ba2\u5355\u6570\u3002\u5982\u679c\u65f6\u523bs\u548c\u5f53\u524d\u65f6\u523b\u63a5\u8fd1\u7684\u8bdd\uff0c\u5b9e\u65f6\u5e94\u7b54\u7387\u5c31\u53ef\u80fd\u504f\u4f4e\u3002",
               "warn":0
            }
         ]
      },
      {
         "name":"\u5feb\u7684\u5bfc\u6d41\u9884\u7ea6\u8ba2\u5355",
         "items":[
            {
               "name":"\u547c\u53eb\u91cf",
               "id":"monitor_taxi_kuaidi_reservation_order_call_num",
               "title":"\u6309\u547c\u53eb\u65f6\u95f4\u7edf\u8ba1\u3002\u65b0\u63d2\u5165\u7684kuaidi_oid!=0\u7684type=1\u7684\u8ba2\u5355. dataSource=order_b"
            },
            {
               "name":"\u6210\u4ea4\u91cf",
               "id":"monitor_taxi_kuaidi_reservation_order_succ_num",
               "title":"\u6309\u547c\u53eb\u65f6\u95f4\u7edf\u8ba1\u3002type=1 && kuaidi_oid!=0 && \u8ba2\u5355\u72b6\u6001\u4ece0\u53d8\u4e3a1,2,3,11. dataSource=order_b",
               "warn":1
            },
            {
               "name":"\u5e94\u7b54\u7387",
               "id":"monitor_taxi_kuaidi_reservation_order_succ_rate",
               "title":"\u6210\u4ea4\u91cf\/\u547c\u53eb\u91cf.\u65f6\u523bs\u7684\u5e94\u7b54\u7387 = \u65f6\u523bs\u5206\u949f\u547c\u53eb\u7684\u5230\u5f53\u524d\u65f6\u523b\u88ab\u5e94\u7b54\u6570 \/ \u65f6\u523bs\u5206\u949f\u547c\u53eb\u8ba2\u5355\u6570\u3002\u5982\u679c\u65f6\u523bs\u548c\u5f53\u524d\u65f6\u523b\u63a5\u8fd1\u7684\u8bdd\uff0c\u5b9e\u65f6\u5e94\u7b54\u7387\u5c31\u53ef\u80fd\u504f\u4f4e.",
               "warn":0
            }
         ]
      },
      {
         "name":"\u53f8\u673a\u4f53\u9a8c",
         "items":[
            {
               "name":"PUSH\u53f8\u673a\u5728\u7ebf",
               "id":"monitor_taxi_driver_push_online",
               "title":"API\u63a5\u53e3\u83b7\u53d6\u3002\u6bcf5\u5206\u949f\u8bbf\u95ee\u4e00\u6b21\u3002aggregations=count(driver_count_sum). dataSource=monitor_taxi_push_driver."
            },
            {
               "name":"\u53f8\u673a\u5728\u7ebf",
               "id":"monitor_taxi_driver_online",
               "title":"API\u63a5\u53e3\u83b7\u53d6\u3002\u6bcf5\u5206\u949f\u8bbf\u95ee\u4e00\u6b21\u3002aggregations=count(online_cnt_sum). dataSource=monitor_taxi_driver_online"
            },
            {
               "name":"\u70b9\u62a2\u53f8\u673a\u6570",
               "id":"monitor_taxi_strive_driver_num",
               "title":"\u8ba2\u5355\u72b6\u6001\u4ece0\u53d8\u4e3a1\u3002aggregations:COUNT(DISTINCT(driverid)) . datasource=order_b"
            }
         ]
      },
      {
         "name":"\u652f\u4ed8\u76d1\u63a7",
         "items":[
            {
               "name":"\u652f\u4ed8\u53d1\u8d77\u6570",
               "id":"monitor_phoenix_pay_taxi_start_num",
               "title":"phoenix\u4e2d\u51fa\u79df\u8f66+\u626b\u7801\u652f\u4ed8"
            },
            {
               "name":"\u652f\u4ed8\u5ef6\u8fdf\u7387",
               "id":"monitor_phoenix_pay_taxi_delay_rate",
               "title":"\u5ef6\u8fdf\u6570\/\u652f\u4ed8\u6570",
               "warn":0
            },
            {
               "name":"\u652f\u4ed8\u6210\u529f\u6570",
               "id":"monitor_phoenix_pay_taxi_succ_num",
               "title":"phoenix\u4e2d\u51fa\u79df\u8f66+\u626b\u7801\u652f\u4ed8"
            },
            {
               "name":"\u652f\u4ed8\u6210\u529f\u91d1\u989d",
               "id":"monitor_phoenix_pay_taxi_succ_money",
               "title":"phoenix\u4e2d\u51fa\u79df\u8f66+\u626b\u7801\u652f\u4ed8"
            }
         ]
      },
      {
         "name":"\u5fae\u4fe1\u652f\u4ed8",
         "items":[
            {
               "name":"\u652f\u4ed8\u53d1\u8d77\u6570",
               "id":"monitor_phoenix_pay_weixin_pay_start_num",
               "title":"\u6309\u7167\u5fae\u4fe1\u652f\u4ed8\u53d1\u8d77\u65f6\u95f4\u7edf\u8ba1\u3002product_line=100 && channel=127 .dataSource=monitor_phoenix_pay_order_detail "
            },
            {
               "name":"\u652f\u4ed8\u5ef6\u8fdf\u7387",
               "id":"monitor_phoenix_pay_weixin_pay_delay_rate",
               "title":"\u5ef6\u8fdf\u6570\/\u652f\u4ed8\u6570",
               "warn":0
            },
            {
               "name":"\u652f\u4ed8\u6210\u529f\u6570",
               "id":"monitor_phoenix_pay_weixin_pay_succ_num",
               "title":"\u6309\u7167\u5fae\u4fe1\u652f\u4ed8\u6210\u529f\u65f6\u95f4\u7edf\u8ba1\u3002product_line=100 && channel=127. dataSource=monitor_phoenix_pay_order_detail"
            },
            {
               "name":"\u652f\u4ed8\u6210\u529f\u91d1\u989d",
               "id":"monitor_phoenix_pay_weixin_pay_succ_money",
               "title":"\u6309\u7167\u5fae\u4fe1\u652f\u4ed8\u6210\u529f\u65f6\u95f4\u7edf\u8ba1\u3002product_line=100 && channel=127. dataSource=monitor_phoenix_pay_order_detail"
            }
         ]
      },
      {
         "name":"\u652f\u4ed8\u5b9d\u652f\u4ed8",
         "items":[
            {
               "name":"\u652f\u4ed8\u53d1\u8d77\u6570",
               "id":"monitor_phoenix_pay_ali_pay_start_num",
               "title":"product_line=100 && channel=128. dataSource=monitor_phoenix_pay_order_detail"
            },
            {
               "name":"\u652f\u4ed8\u5ef6\u8fdf\u7387",
               "id":"monitor_phoenix_pay_ali_pay_delay_rate",
               "title":"\u5ef6\u8fdf\u6570\/\u652f\u4ed8\u6570",
               "warn":0
            },
            {
               "name":"\u652f\u4ed8\u6210\u529f\u6570",
               "id":"monitor_phoenix_pay_ali_pay_succ_num",
               "title":"product_line=100 && channel=128. dataSource=monitor_phoenix_pay_order_detail"
            },
            {
               "name":"\u652f\u4ed8\u6210\u529f\u91d1\u989d",
               "id":"monitor_phoenix_pay_ali_pay_succ_money",
               "title":"product_line=100 && channel=128. dataSource=monitor_phoenix_pay_order_detail"
            }
         ]
      },
      {
         "name":"\u624bQ\u652f\u4ed8",
         "items":[
            {
               "name":"\u652f\u4ed8\u53d1\u8d77\u6570",
               "id":"monitor_phoenix_pay_qq_pay_start_num",
               "title":"product_line=100 && channel=130 . dataSource=monitor_phoenix_pay_order_detail"
            },
            {
               "name":"\u652f\u4ed8\u5ef6\u8fdf\u7387",
               "id":"monitor_phoenix_pay_qq_pay_delay_rate",
               "title":"\u5ef6\u8fdf\u6570\/\u652f\u4ed8\u6570",
               "warn":0
            },
            {
               "name":"\u652f\u4ed8\u6210\u529f\u6570",
               "id":"monitor_phoenix_pay_qq_pay_succ_num",
               "title":"product_line=100 && channel=130 . dataSource=monitor_phoenix_pay_order_detail"
            },
            {
               "name":"\u652f\u4ed8\u6210\u529f\u91d1\u989d",
               "id":"monitor_phoenix_pay_qq_pay_succ_money",
               "title":"product_line=100 && channel=130 . dataSource=monitor_phoenix_pay_order_detail"
            }
         ]
      },
      {
         "name":"\u6ef4\u7c73\u53ca\u5e73\u53f0\u5956\u52b1",
         "items":[
            {
               "name":"\u6ef4\u7c73\u5956\u52b1",
               "id":"monitor_taxi_dimi_rewards_num",
               "title":"\u6309\u5956\u52b1\u65f6\u95f4\u7edf\u8ba1\u3002orderscore>0 && status=1"
            },
            {
               "name":"\u6ef4\u7c73\u6263\u9664",
               "id":"monitor_taxi_dimi_deduct_num",
               "title":"\u6309\u6263\u9664\u65f6\u95f4\u7edf\u8ba1\u3002orderscore<0 && status=1"
            },
            {
               "name":"\u5e73\u53f0\u5956\u52b1\u91d1\u989d",
               "id":"monitor_taxi_platform_rewards_money",
               "title":"\u6309\u5956\u52b1\u65f6\u95f4\u7edf\u8ba1\u3002bonus>0"
            }
         ]
      },
      {
         "name":"\u4e58\u5ba2",
         "items":[
            {
               "name":"\u65b0\u589e\u6ce8\u518c\u6570",
               "id":"monitor_taxi_passenger_new_reg_num",
               "title":"\u6309\u6ce8\u518c\u65f6\u95f4\u7edf\u8ba1.\u5f53\u524d\u63d2\u5165\u5230passenger\u8868\u7684\u6570\u91cf"
            },
            {
               "name":"\u6ef4\u6ef4\u65b0\u589e\u6ce8\u518c\u6570",
               "id":"monitor_taxi_didi_passenger_new_reg_num",
               "title":"\u6309\u6ce8\u518c\u65f6\u95f4\u7edf\u8ba1\u3002 \u5f53\u524d\u63d2\u5165\u5230passenger\u8868\u7684channel\uff01=1361\u7684\u6570\u91cf"
            },
            {
               "name":"\u5feb\u7684\u5bfc\u6d41\u65b0\u589e\u6ce8\u518c\u6570",
               "id":"monitor_taxi_kuaidi_passenger_new_reg_num",
               "title":"\u6309\u6ce8\u518c\u65f6\u95f4\u7edf\u8ba1\u3002\u5f53\u524d\u63d2\u5165\u5230passenger\u8868\u7684channel=1361\u7684\u6570\u91cf"
            }
         ]
      },
      {
         "name":"\u5206\u4eab\u7ea2\u5305\u76d1\u63a7",
         "items":[
            {
               "name":"\u51fa\u79df\u8f66\u53d1\u653e\u4f18\u60e0\u5238\u6570",
               "id":"monitor_taxi_quan_send_num",
               "title":"\u6309\u53d1\u5238\u65f6\u95f4\u7edf\u8ba1.\u5f53\u524d\u63d2\u5165\u5230quan_request \u3002product_id=100"
            },
            {
               "name":"\u4e13\u8f66\u53d1\u653e\u4f18\u60e0\u5238\u6570",
               "id":"monitor_zhuanche_quan_send_num",
               "title":"\u6309\u53d1\u5238\u65f6\u95f4\u7edf\u8ba1\u3002\u5f53\u524d\u63d2\u5165\u5230quan_request \u3002product_id=200"
            },
            {
               "name":"\u5feb\u8f66\u53d1\u653e\u4f18\u60e0\u5238\u6570",
               "id":"monitor_kuaiche_quan_send_num",
               "title":"\u6309\u53d1\u5238\u65f6\u95f4\u7edf\u8ba1\u3002\u5f53\u524d\u63d2\u5165\u5230quan_request \u3002product_id=210"
            },
            {
               "name":"\u987a\u98ce\u8f66\u53d1\u653e\u4f18\u60e0\u5238\u6570",
               "id":"monitor_shunfengche_quan_send_num",
               "title":"\u6309\u53d1\u5238\u65f6\u95f4\u7edf\u8ba1\u3002\u5f53\u524d\u63d2\u5165\u5230quan_request \u3002product_id=150",
               "warn":0
            },
            {
               "name":"\u5df4\u58eb\u53d1\u653e\u4f18\u60e0\u5238\u6570",
               "id":"monitor_bus_quan_send_num",
               "title":"\u6309\u53d1\u5238\u65f6\u95f4\u7edf\u8ba1\u3002\u5f53\u524d\u63d2\u5165\u5230quan_request \u3002product_id=184"
            }
         ]
      },
      {
         "name":"webapp",
         "items":[
            {
               "name":"\u5fae\u4fe1\u8ba2\u5355\u91cf",
               "id":"monitor_taxi_webapp_channel_weixin_order_num",
               "title":"\u6309\u547c\u53eb\u65f6\u95f4\u7edf\u8ba1\u3002\u5f53\u524d\u63d2\u5165\u5230order_b\u8868\u7684channel=1200",
               "druidDataSource":"m2_dc_db_recentorder_fmt_001"
            },
            {
               "name":"\u5fae\u4fe1\u6210\u4ea4\u91cf",
               "id":"monitor_taxi_webapp_channel_weixin_succ_num",
               "title":"\u6309\u547c\u53eb\u65f6\u95f4\u7edf\u8ba1\u3002order_b\u8868\u7684channel=1200\uff0cstatus\u4ece0\u53d8\u4e3a1,2,3,11",
               "druidDataSource":"m2_dc_db_recentorder_fmt_001"
            },
            {
               "name":"\u5fae\u4fe1\u53d1\u5355\u6210\u529f\u7387",
               "id":"monitor_taxi_webapp_channel_weixin_succ_rate",
               "title":"\u6210\u5355\u91cf\/\u547c\u53eb\u91cf",
               "warn":0
            },
            {
               "name":"\u652f\u4ed8\u5b9d\u8ba2\u5355\u91cf",
               "id":"monitor_taxi_webapp_channel_alipay_order_num",
               "title":"\u6309\u547c\u53eb\u65f6\u95f4\u7edf\u8ba1\u3002\u5f53\u524d\u63d2\u5165\u5230order_b\u8868\u7684channel=1300",
               "druidDataSource":"m2_dc_db_recentorder_fmt_001"
            },
            {
               "name":"\u652f\u4ed8\u5b9d\u6210\u4ea4\u91cf",
               "id":"monitor_taxi_webapp_channel_alipay_succ_num",
               "title":"\u6309\u547c\u53eb\u65f6\u95f4\u7edf\u8ba1\u3002order_b\u8868\u7684channel=1300\uff0cstatus\u4ece0\u53d8\u4e3a1,2,3,11",
               "druidDataSource":"m2_dc_db_recentorder_fmt_001"
            },
            {
               "name":"\u652f\u4ed8\u5b9d\u53d1\u5355\u6210\u529f\u7387",
               "id":"monitor_taxi_webapp_channel_alipay_succ_rate",
               "title":"\u6210\u5355\u91cf\/\u547c\u53eb\u91cf",
               "warn":0
            },
            {
               "name":"\u624bQ\u8ba2\u5355\u91cf",
               "id":"monitor_taxi_webapp_channel_qq_order_num",
               "title":"\u5f53\u524d\u63d2\u5165\u5230order_b\u8868\u7684channel=1234"
            },
            {
               "name":"\u624bQ\u6210\u4ea4\u91cf",
               "id":"monitor_taxi_webapp_channel_qq_succ_num",
               "title":"order_b\u8868\u7684channel=1234\uff0cstatus\u4ece0\u53d8\u4e3a1,2,3,11"
            },
            {
               "name":"\u624bQ\u53d1\u5355\u6210\u529f\u7387",
               "id":"monitor_taxi_webapp_channel_qq_succ_rate",
               "title":"\u6210\u5355\u91cf\/\u547c\u53eb\u91cf",
               "warn":0
            },
            {
               "name":"\u901a\u7528\u6e20\u9053\u8ba2\u5355\u91cf",
               "id":"monitor_taxi_webapp_channel_common_order_num",
               "title":"\u5f53\u524d\u63d2\u5165\u5230order_b\u8868\u7684channel!=1300 && channel!=1200 && channel!=1234"
            },
            {
               "name":"\u901a\u7528\u6e20\u9053\u6210\u4ea4\u91cf",
               "id":"monitor_taxi_webapp_channel_common_succ_num",
               "title":"order_b\u8868\u7684channel!=1300 && channel!=1200 && channel!=1234 \u4e14 status\u4ece0\u53d8\u4e3a1,2,3,11"
            },
            {
               "name":"\u901a\u7528\u6e20\u9053\u53d1\u5355\u6210\u529f\u7387",
               "id":"monitor_taxi_webapp_channel_common_succ_rate",
               "title":"\u6210\u4ea4\u91cf\/\u8ba2\u5355\u91cf",
               "warn":0
            }
         ]
      },
      {
         "name":"\u52a8\u6001\u8c03\u4ef7",
         "items":[
            {
               "name":"\u603b\u5192\u6ce1\u6570",
               "id":"monitor_taxi_dynamic_price_total_request",
               "title":""
            },
            {
               "name":"\u8c03\u4ef7\u5192\u6ce1\u6570",
               "id":"monitor_taxi_dynamic_price_b",
               "title":""
            },
            {
               "name":"\u8c03\u4ef7\u53d1\u5355\u6570",
               "id":"monitor_taxi_dynamic_price_e",
               "title":""
            },
            {
               "name":"\u8c03\u4ef7\u6bd4\u4f8b",
               "id":"monitor_taxi_dynamic_price_tiaojia_rate",
               "title":"",
               "warn":0
            },
            {
               "name":"\u8c03\u4ef7\u63a5\u53d7\u7387",
               "id":"monitor_taxi_dynamic_price_tiaojia_accept_rate",
               "title":"",
               "warn":0
            },
            {
               "name":"\u672a\u8c03\u4ef7\u63a5\u53d7\u7387",
               "id":"monitor_taxi_dynamic_price_notiaojia_accept_rate",
               "title":"",
               "warn":0
            },
            {
               "name":"\u8c03\u4ef7\u6210\u4ea4\u7387",
               "id":"monitor_taxi_dynamic_price_tiaojia_deal_rate",
               "title":"",
               "warn":0
            },
            {
               "name":"\u5e73\u5747\u8c03\u4ef7\u91d1\u989d",
               "id":"monitor_taxi_dynamic_price_tiaojia_avg_money",
               "title":"",
               "warn":0
            }
         ]
      }
   ],
   "sfc_items":[
      {
         "name":"\u547c\u53eb\u4e0e\u5e94\u7b54",
         "items":[
            {
               "name":"\u547c\u53eb\u91cf",
               "id":"monitor_shunfengche_call_num",
               "title":"\u6309\u547c\u53eb\u65f6\u95f4\u7edf\u8ba1\u3002\u5f53\u524d\u65b0\u63d2\u5165\u3002\u6570\u636e\u6e90\uff1aorder_info",
               "druidDataSource":"m2_order_info_extra"
            },
            {
               "name":"\u5e94\u7b54\u91cf",
               "id":"monitor_shunfengche_answer_num",
               "title":"\u6309\u5e94\u7b54\u65f6\u95f4\u7edf\u8ba1 status\u4ece0\u53d8\u4e3a1\u3002\u6570\u636e\u6e90\uff1aorder_info",
               "druidDataSource":"m2_order_info_extra"
            },
            {
               "name":"\u5e94\u7b54\u7387",
               "id":"monitor_shunfengche_yingda_rate",
               "title":"\u6309\u547c\u53eb\u65f6\u95f4\u7edf\u8ba1\u5e94\u7b54\u91cf\u548c\u547c\u53eb\u91cf\uff0c\u7136\u540e\u7528\u5e94\u7b54\u91cf\/\u547c\u53eb\u91cf",
               "warn":0
            },
            {
               "name":"\u652f\u4ed8\u91cf",
               "id":"monitor_shunfengche_pay_num",
               "title":"\u6309\u652f\u4ed8\u65f6\u95f4\u7edf\u8ba1 status\u53d8\u4e3a3\u3002\u6570\u636e\u6e90\uff1aorder_info",
               "druidDataSource":"m2_order_info_extra"
            },
            {
               "name":"\u4e3b\u52a8\u53d6\u6d88\u91cf",
               "id":"monitor_shunfengche_cancel_num",
               "title":"\u6309\u53d6\u6d88\u65f6\u95f4\u7edf\u8ba1status\u53d8\u4e3a10,12\u3002\u6570\u636e\u6e90\uff1aorder_info"
            },
            {
               "name":"\u63a5\u5355\u524d\u53d6\u6d88\u91cf",
               "id":"monitor_shunfengche_before_accept_cancel_num",
               "title":"\u6309\u53d6\u6d88\u65f6\u95f4\u7edf\u8ba1 \u975e\u5220\u9664\u7c7b\u578b\u3002status\u53d8\u4e3a10\u3002\u6570\u636e\u6e90\uff1aorder_info",
               "druidDataSource":"m2_order_info_extra"
            },
            {
               "name":"\u63a5\u5355\u540e\u53d6\u6d88\u91cf",
               "id":"monitor_shunfengche_after_accept_cancel_num",
               "title":"\u6309\u53d6\u6d88\u65f6\u95f4\u7edf\u8ba1 status\u53d8\u4e3a12\u3002\u6570\u636e\u6e90\uff1aorder_info",
               "druidDataSource":"m2_order_info_extra"
            },
            {
               "name":"\u660e\u65e5\u51fa\u884c\u547c\u53eb\u91cf",
               "id":"monitor_shunfengche_tommorow_call_num",
               "title":"\u6309\u51fa\u884c\u65f6\u95f4\u7edf\u8ba1\uff08\u51fa\u884c\u65f6\u95f4\u5728\u660e\u5929\uff09\u3002\u5f53\u524d\u63d2\u5165\u7684setup_time\u7684\u8303\u56f4\u662f\u660e\u5929\u547c\u53eb\u3002\u6570\u636e\u6e90\uff1aorder_info"
            },
            {
               "name":"\u5e73\u5747\u62a2\u5355\u65f6\u95f4\uff08\u5206\uff09",
               "id":"monitor_shunfengche_avg_competing_order_time",
               "title":"\u603b\u62a2\u5355\u65f6\u95f4\/\u62a2\u5355\u91cf",
               "warn":0
            },
            {
               "name":"\u987a\u8def\u8ba2\u5355\u62a2\u5355\u91cf",
               "id":"monitor_shunfengche_shunludan_num",
               "title":"\u6839\u636e\u62a2\u5355\u65f6\u95f4\u7edf\u8ba1 status\u53d8\u4e3a1 and route_id!=0\u3002\u6570\u636e\u6e90\uff1aorder_info",
               "druidDataSource":"m2_order_info_extra"
            },
            {
               "name":"\u9644\u8fd1\u8ba2\u5355\u62a2\u5355\u91cf",
               "id":"monitor_shunfengche_fujindan_num",
               "title":"\u6839\u636e\u62a2\u5355\u65f6\u95f4\u7edf\u8ba1 status\u53d8\u4e3a1 and route_id=0\u3002\u6570\u636e\u6e90\uff1aorder_info",
               "druidDataSource":"m2_order_info_extra"
            },
            {
               "name":"\u641c\u7d22\u4e58\u5ba2\u62a2\u5355\u91cf",
               "id":"monitor_shunfengche_searchpassenger_num",
               "title":"\u6839\u636e\u62a2\u5355\u65f6\u95f4\u7edf\u8ba1 status\u53d8\u4e3a1 and route_id>=4200000000\u3002\u6570\u636e\u6e90\uff1aorder_info"
            },
            {
               "name":"\u53cd\u4f5c\u5f0a\u547d\u4e2d\u8ba2\u5355\u6570",
               "id":"monitor_shunfengche_fanzuobi_order_num",
               "title":"\u6839\u636e\u5224\u5b9a\u4f5c\u5f0a\u65f6\u95f4\u7edf\u8ba1antispam_code!=0\u3002\u6570\u636e\u6e90\uff1aallowanceinfo"
            },
            {
               "name":"\u53f8\u673a\u8865\u8d34",
               "id":"monitor_shunfengche_driver_subsidy_num",
               "title":"\u6839\u636e\u8865\u8d34\u65f6\u95f4\u7edf\u8ba1 antispam_code = 0\u3002\u6570\u636e\u6e90\uff1aallowanceinfo"
            },
            {
               "name":"\u987a\u8def\u8ba2\u5355Push\u6570",
               "id":"monitor_shunfengche_shunludan_push_num",
               "title":"\u6309push\u65f6\u95f4\u7edf\u8ba1\u3002type=beatles_push\u3002\u6570\u636e\u6e90\uff1aflume_beatles_route_order_push"
            },
            {
               "name":"\u7528\u5238\u5f20\u6570",
               "id":"monitor_shunfengche_quan_pay_num",
               "title":"\u66f4\u65b0\u7c7b\u578b\u3002archive=0 && status=1 && channel_id=110 && product_line=150.\u6570\u636e\u6e90\uff1apay_order_detail"
            },
            {
               "name":"\u7528\u5238\u91d1\u989d(\u5143)",
               "id":"monitor_shunfengche_quan_pay_money",
               "title":"\u66f4\u65b0\u7c7b\u578b\u3002archive=0 && status=1 && channel_id=110 && product_line=150.\u6570\u636e\u6e90\uff1apay_order_detail"
            },
            {
               "name":"\u613f\u610f\u62fc\u8f66\u8ba2\u5355\u91cf",
               "id":"monitor_shunfengche_pinche_num",
               "title":"\u5f53\u524d\u63d2\u5165is_carpool=1\u3002\u6570\u636e\u6e90\uff1aorder_info"
            }
         ]
      },
      {
         "name":"\u51fa\u884c\u8ba2\u5355\u4e0e\u5e94\u7b54",
         "items":[
            {
               "name":"\u51fa\u884c\u8ba2\u5355\u91cf",
               "id":"monitor_shunfengche_chuxing_order_num",
               "title":"\u6309\u51fa\u884c\u65f6\u95f4\u7edf\u8ba1\u3002\u4ece\u7f13\u5b58\u4e2d\u83b7\u53d6\u6570\u636e\u3002ckv_id=sfc_setup_cnt"
            },
            {
               "name":"\u51fa\u884c\u8ba2\u5355\u5e94\u7b54\u91cf",
               "id":"monitor_shunfengche_chuxing_order_answer_num",
               "title":"\u6309\u51fa\u884c\u65f6\u95f4\u7edf\u8ba1\u3002\u4ece\u7f13\u5b58\u4e2d\u83b7\u53d6\u6570\u636e\u3002ckv_id=sfc_setup_succcnt"
            },
            {
               "name":"\u672a\u88ab\u5e94\u7b54\u51fa\u884c\u8ba2\u5355\u91cf",
               "id":"monitor_shunfengche_chuxing_order_no_answer_num",
               "title":"\u6309\u51fa\u884c\u65f6\u95f4\u7edf\u8ba1.\u4ece\u7f13\u5b58\u4e2d\u83b7\u53d6\u6570\u636e\u3002ckv_id=sfc_setup_failcnt"
            },
            {
               "name":"\u51fa\u884c\u8ba2\u5355\u5e94\u7b54\u7387",
               "id":"monitor_shunfengche_chuxing_order_answer_num_rate",
               "title":"\u6309\u51fa\u884c\u65f6\u95f4\u7edf\u8ba1.\u5e94\u7b54\u91cf\/\u8ba2\u5355\u91cf",
               "warn":0
            }
         ]
      },
      {
         "name":"\u53f8\u673a\u5728\u7ebf",
         "items":[
            {
               "name":"\u603b\u53f8\u673a\u5728\u7ebf\u6570",
               "id":"monitor_shunfengche_total_driver_num",
               "title":"\u4ece\u65e5\u5fd7\u53d6\u6570\u3002\u6570\u636e\u6e90\uff1aflume_beatles_order"
            }
         ]
      },
      {
         "name":"\u8def\u7ebf\u76f8\u5173",
         "items":[
            {
               "name":"\u56fa\u5b9a\u8def\u7ebf\u5217\u8868\u5c55\u73b0\u6b21\u6570",
               "id":"monitor_shunfengche_fix_route_list_show_num",
               "title":"\u4ece\u65e5\u5fd7\u53d6\u6570\u3002type=beatles_match_strive_order\u3002\u6570\u636e\u6e90\uff1aflume_beatles_route"
            },
            {
               "name":"\u4e34\u65f6\u8def\u7ebf\u5217\u8868\u5c55\u73b0\u6b21\u6570",
               "id":"monitor_shunfengche_temp_route_list_show_num",
               "title":"\u4ece\u65e5\u5fd7\u53d6\u6570\u3002type=beatles_tmp_strive_order\u3002\u6570\u636e\u6e90\uff1aflume_beatles_route"
            },
            {
               "name":"\u9644\u8fd1\u5217\u8868\u5c55\u73b0\u6b21\u6570",
               "id":"monitor_shunfengche_nearby_list_show_num",
               "title":"\u4ece\u65e5\u5fd7\u53d6\u6570\u3002type=beatles_around_order\u3002\u6570\u636e\u6e90\uff1aflume_beatles_route"
            },
            {
               "name":"\u56fa\u5b9a\u8def\u7ebf\u5217\u8868\u8ba2\u5355\u91cf",
               "id":"monitor_shunfengche_fix_route_list_order_num",
               "title":"\u4ece\u65e5\u5fd7\u53d6\u6570\u3002type=beatles_match_strive_order\u3002\u6570\u636e\u6e90\uff1aflume_beatles_route"
            },
            {
               "name":"\u4e34\u65f6\u8def\u7ebf\u5217\u8868\u8ba2\u5355\u91cf",
               "id":"monitor_shunfengche_temp_route_list_order_num",
               "title":"\u4ece\u65e5\u5fd7\u53d6\u6570\u3002type=beatles_tmp_strive_order\u3002\u6570\u636e\u6e90\uff1aflume_beatles_route"
            },
            {
               "name":"\u9644\u8fd1\u5217\u8868\u8ba2\u5355\u91cf",
               "id":"monitor_shunfengche_nearby_list_order_num",
               "title":"\u4ece\u65e5\u5fd7\u53d6\u6570\u3002type=beatles_around_order\u3002\u6570\u636e\u6e90\uff1aflume_beatles_route"
            },
            {
               "name":"\u56fa\u5b9a\u8def\u7ebflbs\u622a\u65ad\u6bd4\u4f8b",
               "id":"monitor_shunfengche_fix_route_lbs_rate",
               "title":"\u9644\u8fd1\u8def\u7ebflbs\u67e5\u8be2\u91cf\/\u9644\u8fd1\u8def\u7ebf\u603b\u67e5\u8be2\u91cf",
               "warn":0
            },
            {
               "name":"\u4e34\u65f6\u8def\u7ebflbs\u622a\u65ad\u6bd4\u4f8b",
               "id":"monitor_shunfengche_temp_route_lbs_rate",
               "title":"\u4e34\u65f6\u8def\u7ebflbs\u67e5\u8be2\u91cf\/\u4e34\u65f6\u8def\u7ebf\u603b\u67e5\u8be2\u91cf",
               "warn":0
            }
         ]
      },
      {
         "name":"webapp",
         "items":[
            {
               "name":"\u652f\u4ed8\u5b9d\u547c\u53eb\u91cf",
               "id":"monitor_shunfengche_webapp_500641_call_num",
               "title":"\u5f53\u524d\u63d2\u5165channel=500641\u3002\u6570\u636e\u6e90\u4e3aorder_info"
            },
            {
               "name":"\u652f\u4ed8\u5b9d\u5e94\u7b54\u91cf",
               "id":"monitor_shunfengche_webapp_500641_answer_num",
               "title":"\u72b6\u6001\u4ece0\u53d8\u4e3a1\u3002channel=500641\u3002\u6570\u636e\u6e90\u4e3aorder_info"
            },
            {
               "name":"\u5fae\u4fe1\u547c\u53eb\u91cf",
               "id":"monitor_shunfengche_webapp_500642_call_num",
               "title":"\u5f53\u524d\u63d2\u5165channel=500642\u3002\u6570\u636e\u6e90\u4e3aorder_info"
            },
            {
               "name":"\u5fae\u4fe1\u5e94\u7b54\u91cf",
               "id":"monitor_shunfengche_webapp_500642_answer_num",
               "title":"\u72b6\u6001\u4ece0\u53d8\u4e3a1\u3002channel=500642\u3002\u6570\u636e\u6e90\u4e3aorder_info"
            },
            {
               "name":"\u5176\u4ed6\u547c\u53eb\u91cf",
               "id":"monitor_shunfengche_webapp_500643_call_num",
               "title":"\u5f53\u524d\u63d2\u5165channel=500643\u3002\u6570\u636e\u6e90\u4e3aorder_info"
            },
            {
               "name":"\u5176\u4ed6\u5e94\u7b54\u91cf",
               "id":"monitor_shunfengche_webapp_500643_answer_num",
               "title":"\u72b6\u6001\u4ece0\u53d8\u4e3a1\u3002channel=500643\u3002\u6570\u636e\u6e90\u4e3aorder_info"
            }
         ]
      },
      {
         "name":"\u652f\u4ed8",
         "items":[
            {
               "name":"\u4e58\u5ba2\u5b9e\u9645\u652f\u4ed8\u91d1\u989d",
               "id":"monitor_shunfengche_pay_passenger_pay_amount",
               "title":"beatles_pay_total_amount_static:passenger_pay_amount"
            },
            {
               "name":"\u8f66\u4e3b\u5230\u8d26\u91d1\u989d",
               "id":"monitor_shunfengche_pay_driver_amount",
               "title":"beatles_pay_total_amount_static:driver_amount"
            },
            {
               "name":"\u987a\u98ce\u8f66\u670d\u52a1\u8d39\u91d1\u989d",
               "id":"monitor_shunfengche_pay_beatles_amount",
               "title":"beatles_pay_total_amount_static:beatles_amount"
            }
         ]
      }
   ],
   "dj_items":[
      {
         "name":"\u603b\u4f53\u76d1\u63a7",
         "items":[
            {
               "name":"\u5168\u91cf\u8ba2\u5355\u6570",
               "id":"monitor_dj_ord_total_cnt",
               "title":"\u7531\u4ee3\u9a7e\u4e1a\u52a1\u7ebf\u7edf\u8ba1\uff0c\u76f4\u63a5\u53d6\u6570\u3002\u5f53\u524d\u63d2\u5165risk_type!=3.\u6570\u636e\u6e90\uff1avalet_order"
            },
            {
               "name":"\u7ebf\u4e0a\u8ba2\u5355\u6570",
               "id":"monitor_dj_ord_online_cnt",
               "title":"\u7531\u4ee3\u9a7e\u4e1a\u52a1\u7ebf\u7edf\u8ba1\uff0c\u76f4\u63a5\u53d6\u6570\u3002\u5f53\u524d\u63d2\u5165risk_type=1 && send_type=1.\u6570\u636e\u6e90\uff1avalet_order"
            },
            {
               "name":"400\u4e0b\u5355\u6570",
               "id":"monitor_dj_ord_400_cnt",
               "title":"\u7531\u4ee3\u9a7e\u4e1a\u52a1\u7ebf\u7edf\u8ba1\uff0c\u76f4\u63a5\u53d6\u6570.\u5f53\u524d\u63d2\u5165risk_type=1 && send_type=3.\u6570\u636e\u6e90\uff1avalet_order"
            },
            {
               "name":"\u53f8\u673a\u62a5\u5355\u6570",
               "id":"monitor_dj_ord_driver_cnt",
               "title":"\u7531\u4ee3\u9a7e\u4e1a\u52a1\u7ebf\u7edf\u8ba1\uff0c\u76f4\u63a5\u53d6\u6570.\u5f53\u524d\u63d2\u5165risk_type=1 && send_type=2.\u6570\u636e\u6e90\uff1avalet_order"
            },
            {
               "name":"\u9759\u9ed8\u5355\u6570",
               "id":"monitor_dj_ord_jingmo_cnt",
               "title":"\u7531\u4ee3\u9a7e\u4e1a\u52a1\u7ebf\u7edf\u8ba1\uff0c\u76f4\u63a5\u53d6\u6570.\u5f53\u524d\u63d2\u5165risk_type=4.\u6570\u636e\u6e90\uff1avalet_order"
            },
            {
               "name":"\u5237\u5355\u6570",
               "id":"monitor_dj_ord_shuadan_cnt",
               "title":"\u7531\u4ee3\u9a7e\u4e1a\u52a1\u7ebf\u7edf\u8ba1\uff0c\u76f4\u63a5\u53d6\u6570.risk_type\u53d8\u4e3a2.\u6570\u636e\u6e90\uff1avalet_order"
            },
            {
               "name":"\u62a2\u5355\u6210\u529f\u8ba2\u5355\u6570",
               "id":"monitor_dj_ord_strive_succ_cnt",
               "title":"\u7531\u4ee3\u9a7e\u4e1a\u52a1\u7ebf\u7edf\u8ba1\uff0c\u76f4\u63a5\u53d6\u6570\u3002\u5f53\u524d\u63d2\u5165\u8ba2\u5355\u3002\u6570\u636e\u6e90\uff1abi_valet_order_result_merge"
            },
            {
               "name":"\u7ed3\u675f\u670d\u52a1\u8ba2\u5355\u6570",
               "id":"monitor_dj_ord_finish_service_cnt",
               "title":"\u7531\u4ee3\u9a7e\u4e1a\u52a1\u7ebf\u7edf\u8ba1\uff0c\u76f4\u63a5\u53d6\u6570\u3002t_end_charge_time!=-999 && !=null\u3002\u6570\u636e\u6e90\u4e3abi_valet_order_result_merge"
            },
            {
               "name":"\u652f\u4ed8\u5b8c\u6210\u8ba2\u5355\u6570",
               "id":"monitor_dj_ord_pay_finish_cnt",
               "title":"\u7531\u4ee3\u9a7e\u4e1a\u52a1\u7ebf\u7edf\u8ba1\uff0c\u76f4\u63a5\u53d6\u6570\u3002\u8ba2\u5355\u72b6\u6001\u4ece3\u62164\u53d8\u4e3a5\u62167.\u6570\u636e\u6e90\u4e3abi_trade_order_merge_2"
            },
            {
               "name":"\u6d88\u5355\u6570",
               "id":"monitor_dj_ord_cancle_cnt",
               "title":"\u7531\u4ee3\u9a7e\u4e1a\u52a1\u7ebf\u7edf\u8ba1\uff0c\u76f4\u63a5\u53d6\u6570.\u53d6\u6d88\u7c7b\u578b\u4ece0\u53d8\u4e3a\uff081\uff0c2,3,4,5,6\uff09.\u6570\u636e\u6e90\u4e3avalet_order"
            },
            {
               "name":"\u62a2\u5355\u524d\u6d88\u5355\u6570",
               "id":"monitor_dj_ord_cancle_before_cnt",
               "title":"\u7531\u4ee3\u9a7e\u4e1a\u52a1\u7ebf\u7edf\u8ba1\uff0c\u76f4\u63a5\u53d6\u6570\u3002\u53d6\u6d88\u7c7b\u578b\u53d8\u4e3a1.\u6570\u636e\u6e90\u4e3avalet_order"
            },
            {
               "name":"\u62a2\u5355\u540e\u4e58\u5ba2\u6d88\u5355\u6570",
               "id":"monitor_dj_ord_cancle_after_p_cnt",
               "title":"\u7531\u4ee3\u9a7e\u4e1a\u52a1\u7ebf\u7edf\u8ba1\uff0c\u76f4\u63a5\u53d6\u6570\u3002\u53d6\u6d88\u7c7b\u578b\u53d8\u4e3a2.\u6570\u636e\u6e90\u4e3avalet_order"
            },
            {
               "name":"\u62a2\u5355\u540e\u53f8\u673a\u6d88\u5355\u6570",
               "id":"monitor_dj_ord_cancle_after_d_cnt",
               "title":"\u7531\u4ee3\u9a7e\u4e1a\u52a1\u7ebf\u7edf\u8ba1\uff0c\u76f4\u63a5\u53d6\u6570\u3002\u53d6\u6d88\u7c7b\u578b\u53d8\u4e3a3.\u6570\u636e\u6e90\u4e3avalet_order"
            },
            {
               "name":"\u62a2\u5355\u540e\u5ba2\u670d\u6d88\u5355\u6570",
               "id":"monitor_dj_ord_cancle_after_c_cnt",
               "title":"\u7531\u4ee3\u9a7e\u4e1a\u52a1\u7ebf\u7edf\u8ba1\uff0c\u76f4\u63a5\u53d6\u6570\u3002\u53d6\u6d88\u7c7b\u578b\u53d8\u4e3a4,5,6.\u6570\u636e\u6e90\u4e3avalet_order"
            },
            {
               "name":"\u62a2\u5355\u6210\u529f\u53f8\u673a\u6570",
               "id":"monitor_dj_ord_strive_driver_cnt",
               "title":"\u7531\u4ee3\u9a7e\u4e1a\u52a1\u7ebf\u7edf\u8ba1\uff0c\u76f4\u63a5\u53d6\u6570\u3002\u6570\u636e\u6e90\u4e3abi_valet_order_result_merge"
            },
            {
               "name":"\u63a8\u5355\u8ba2\u5355\u6570",
               "id":"monitor_dj_ord_push_cnt",
               "title":"\u7531\u4ee3\u9a7e\u4e1a\u52a1\u7ebf\u7edf\u8ba1\uff0c\u76f4\u63a5\u53d6\u6570\u3002metric_name=\u63a8\u5355\u65e5\u5fd7\u3002\u6570\u636e\u6e90\u4e3abi_push_order_result_merge"
            },
            {
               "name":"\u5728\u7ebf\u53f8\u673a\u6570",
               "id":"monitor_dj_driver_online_cnt",
               "title":"\u6253\u5f00App\u7684\u53f8\u673a\u6570\uff08\u6709\u5fc3\u8df3\uff09\uff0c\u4f46\u662f\u53f8\u673a\u4e0d\u4e00\u5b9a\u5728\u4e0a\u73ed\u72b6\u6001\uff08\u70b9\u4e0a\u73ed\uff09\u3002\u7531\u4ee3\u9a7e\u4e1a\u52a1\u7ebf\u7edf\u8ba1\uff0c\u76f4\u63a5\u53d6\u6570\u3002\u6570\u636e\u6e90daijia_lbs_driver_pos_his"
            },
            {
               "name":"\u5b9e\u65f6\u6210\u5355\u7387",
               "id":"monitor_dj_deal_rate",
               "title":"\u5b9e\u65f6\u6210\u5355\u7387=\uff08\u62a2\u5355\u6210\u529f\u8ba2\u5355\u6570+\u62a2\u5355\u524d\u6d88\u5355\u6570-\u6d88\u5355\u6570\uff09\/\uff08\u5168\u91cf\u8ba2\u5355\u6570-\u9759\u9ed8\u5355\u6570\uff09"
            }
         ]
      }
   ],
   "zhuanche_items":[
      {
         "name":"\u91cd\u8981\u6307\u6807\u6982\u51b5",
         "items":[
            {
               "name":"\u5b9e\u65f6\u8ba2\u5355\u547c\u53eb\u91cf",
               "id":"monitor_zhuanche_realtime_order_call_num",
               "title":"\u6309\u7167\u8ba2\u5355\u547c\u53eb\u65f6\u95f4\u7edf\u8ba1\u3002type=0 and channel!=1 and channel !=1010000001\u3002dataSource=g_order_a",
               "druidDataSource":"m2_gs_db_gulfstream_g_order_fmt_004"
            },
            {
               "name":"\u5b9e\u65f6\u8ba2\u5355\u6210\u4ea4\u91cf",
               "id":"monitor_zhuanche_realtime_order_deal_num",
               "title":"\u6309\u7167\u8ba2\u5355\u547c\u53eb\u65f6\u95f4\u7edf\u8ba1\u3002type=0 and channel!=1 and channel !=1010000001 and order_status\u53d8\u4e3a5 \u3002dataSource=g_order_a",
               "druidDataSource":"m2_gs_db_gulfstream_g_order_fmt_004"
            },
            {
               "name":"\u603b\u5192\u6ce1\u6570",
               "id":"monitor_zhuanche_dynamic_price_total_request",
               "title":"\u6570\u636e\u6765\u81ea\u52a8\u6001\u8c03\u4ef7\u7edf\u8ba1\u65e5\u5fd7\u3002\u6309\u52a8\u6001\u8c03\u4ef7\u7edf\u8ba1\u65f6\u95f4\u8fdb\u884c\u7edf\u8ba1\u3002\u6bcf5\u5206\u949f\u7edf\u8ba11\u6b21\u3002\u6570\u636e\u6e90\uff1aflume_dynamicprice"
            },
            {
               "name":"\u5b9e\u65f6\u8ba2\u5355\u5e94\u7b54\u7387",
               "id":"monitor_zhuanche_realtime_order_answer_rate",
               "title":"\u65f6\u523bs\u7684\u5e94\u7b54\u7387 = \u65f6\u523bs\u5206\u949f\u547c\u53eb\u7684\u5230\u5f53\u524d\u65f6\u523b\u88ab\u5e94\u7b54\u6570 \/ \u65f6\u523bs\u5206\u949f\u547c\u53eb\u8ba2\u5355\u6570\u3002\u5982\u679c\u65f6\u523bs\u548c\u5f53\u524d\u65f6\u523b\u63a5\u8fd1\u7684\u8bdd\uff0c\u5b9e\u65f6\u5e94\u7b54\u7387\u5c31\u53ef\u80fd\u504f\u4f4e\u3002",
               "warn":0
            },
            {
               "name":"\u603b\u53f8\u673a\u5728\u7ebf\u6570",
               "id":"monitor_zhuanche_driver_online_total_num",
               "title":""
            },
            {
               "name":"\u670d\u52a1\u4e2d\u53f8\u673a\u5728\u7ebf\u6570",
               "id":"monitor_zhuanche_driver_online_service_num",
               "title":""
            },
            {
               "name":"\u7a7a\u95f2\u53f8\u673a\u5728\u7ebf\u6570",
               "id":"monitor_zhuanche_driver_online_free_num",
               "title":""
            },
            {
               "name":"\u670d\u52a1\u53f8\u673a\u6bd4\u4f8b",
               "id":"monitor_zhuanche_driver_online_service_rate",
               "title":"",
               "warn":0
            }
         ]
      },
      {
         "name":"webapp",
         "items":[
            {
               "name":"\u5168\u90e8\u5b9e\u65f6\u8ba2\u5355\u547c\u53eb\u91cf",
               "id":"monitor_zhuanche_webapp_all_rt_order_call_num",
               "title":"\u6309\u7167\u8ba2\u5355\u547c\u53eb\u65f6\u95f4\u7edf\u8ba1\u3002WebApp\u5168\u90e8\u8ba2\u5355 = \u5fae\u4fe1 + \u624bQ + \u652f\u4ed8\u5b9d + \u901a\u7528 + \u5f00\u653e\u5e73\u53f0"
            },
            {
               "name":"\u5168\u90e8\u5b9e\u65f6\u8ba2\u5355\u6210\u4ea4\u91cf",
               "id":"monitor_zhuanche_webapp_all_rt_order_deal_num",
               "title":"\u6309\u7167\u8ba2\u5355\u6210\u4ea4\u65f6\u95f4\u7edf\u8ba1\u3002type=0 and channel =** and order_status\u53d8\u4e3a5 \u3002dataSource=g_order_a"
            },
            {
               "name":"\u5fae\u4fe1\u5b9e\u65f6\u8ba2\u5355\u547c\u53eb\u91cf",
               "id":"monitor_zhuanche_webapp_weixin_rt_order_call_num",
               "title":"\u6309\u7167\u8ba2\u5355\u547c\u53eb\u65f6\u95f4\u7edf\u8ba1\u3002type=0 and channel =1020000001\u3002dataSource=g_order_a"
            },
            {
               "name":"\u5fae\u4fe1\u5b9e\u65f6\u8ba2\u5355\u6210\u4ea4\u91cf",
               "id":"monitor_zhuanche_webapp_weixin_rt_order_deal_num",
               "title":"\u6309\u7167\u8ba2\u5355\u6210\u4ea4\u65f6\u95f4\u7edf\u8ba1\u3002type=0 and channel =1020000001 and order_status\u53d8\u4e3a5 \u3002dataSource=g_order_a"
            },
            {
               "name":"\u624bQ\u5b9e\u65f6\u8ba2\u5355\u547c\u53eb\u91cf",
               "id":"monitor_zhuanche_webapp_qq_rt_order_call_num",
               "title":"\u6309\u7167\u8ba2\u5355\u547c\u53eb\u65f6\u95f4\u7edf\u8ba1\u3002type=0 and channel =1020000002\u3002dataSource=g_order_a"
            },
            {
               "name":"\u624bQ\u5b9e\u65f6\u8ba2\u5355\u6210\u4ea4\u91cf",
               "id":"monitor_zhuanche_webapp_qq_rt_order_deal_num",
               "title":"\u6309\u7167\u8ba2\u5355\u6210\u4ea4\u65f6\u95f4\u7edf\u8ba1\u3002type=0 and channel =1020000002 and order_status\u53d8\u4e3a5 \u3002dataSource=g_order_a"
            },
            {
               "name":"\u652f\u4ed8\u5b9d\u5b9e\u65f6\u8ba2\u5355\u547c\u53eb\u91cf",
               "id":"monitor_zhuanche_webapp_alipay_rt_order_call_num",
               "title":"\u6309\u7167\u8ba2\u5355\u547c\u53eb\u65f6\u95f4\u7edf\u8ba1\u3002type=0 and channel =1020000004\u3002dataSource=g_order_a"
            },
            {
               "name":"\u652f\u4ed8\u5b9d\u5b9e\u65f6\u8ba2\u5355\u6210\u4ea4\u91cf",
               "id":"monitor_zhuanche_webapp_alipay_rt_order_deal_num",
               "title":"\u6309\u7167\u8ba2\u5355\u6210\u4ea4\u65f6\u95f4\u7edf\u8ba1\u3002type=0 and channel =1020000004 and order_status\u53d8\u4e3a5 \u3002dataSource=g_order_a"
            },
            {
               "name":"\u901a\u7528\u5b9e\u65f6\u8ba2\u5355\u547c\u53eb\u91cf",
               "id":"monitor_zhuanche_webapp_common_rt_order_call_num",
               "title":"\u6309\u7167\u8ba2\u5355\u547c\u53eb\u65f6\u95f4\u7edf\u8ba1\u3002type=0 and channel =103****\u3002dataSource=g_order_a"
            },
            {
               "name":"\u901a\u7528\u5b9e\u65f6\u8ba2\u5355\u6210\u4ea4\u91cf",
               "id":"monitor_zhuanche_webapp_common_rt_order_deal_num",
               "title":"\u6309\u7167\u8ba2\u5355\u6210\u4ea4\u65f6\u95f4\u7edf\u8ba1\u3002type=0 and channel =103**** and order_status\u53d8\u4e3a5 \u3002dataSource=g_order_a"
            },
            {
               "name":"\u5f00\u653e\u5e73\u53f0\u5b9e\u65f6\u8ba2\u5355\u547c\u53eb\u91cf",
               "id":"monitor_zhuanche_webapp_open_rt_order_call_num",
               "title":"\u6309\u7167\u8ba2\u5355\u547c\u53eb\u65f6\u95f4\u7edf\u8ba1\u3002type=0 and channel =104****\u3002dataSource=g_order_a"
            },
            {
               "name":"\u5f00\u653e\u5e73\u53f0\u5b9e\u65f6\u8ba2\u5355\u6210\u4ea4\u91cf",
               "id":"monitor_zhuanche_webapp_open_rt_order_deal_num",
               "title":"\u6309\u7167\u8ba2\u5355\u6210\u4ea4\u65f6\u95f4\u7edf\u8ba1\u3002type=0 and channel =104**** and order_status\u53d8\u4e3a5 \u3002dataSource=g_order_a"
            }
         ]
      },
      {
         "name":"\u5b9e\u65f6\u8ba2\u5355",
         "items":[
            {
               "name":"\u5b9e\u65f6\u8ba2\u5355\u547c\u53eb\u91cf",
               "id":"monitor_zhuanche_realtime_order_call_num",
               "title":"\u6309\u7167\u8ba2\u5355\u547c\u53eb\u65f6\u95f4\u7edf\u8ba1\u3002type=0 and channel!=1 and   channel !=1010000001\u3002\u6570\u636e\u6e90\uff1ag_order_a"
            },
            {
               "name":"\u5b9e\u65f6\u8ba2\u5355\u6210\u4ea4\u91cf",
               "id":"monitor_zhuanche_realtime_order_deal_num",
               "title":"\u6309\u7167\u8ba2\u5355\u547c\u53eb\u65f6\u95f4\u7edf\u8ba1\u3002type=0 and channel!=1 and channel !=1010000001 and order_status\u53d8\u4e3a5 \u3002\u6570\u636e\u6e90\uff1ag_order_a"
            },
            {
               "name":"\u603b\u5192\u6ce1\u6570",
               "id":"monitor_zhuanche_dynamic_price_total_request",
               "title":"\u6570\u636e\u6765\u81ea\u52a8\u6001\u8c03\u4ef7\u7edf\u8ba1\u65e5\u5fd7\u3002\u6309\u52a8\u6001\u8c03\u4ef7\u7edf\u8ba1\u65f6\u95f4\u8fdb\u884c\u7edf\u8ba1\u3002\u6bcf5\u5206\u949f\u7edf\u8ba11\u6b21\u3002\u6570\u636e\u6e90\uff1aflume_dynamicprice"
            },
            {
               "name":"\u5b9e\u65f6\u8ba2\u5355\u5e94\u7b54\u524d\u53d6\u6d88\u91cf",
               "id":"monitor_zhuanche_realtime_order_before_deal_cancel_num",
               "title":"\u6309\u7167\u8ba2\u5355\u53d6\u6d88\u65f6\u95f4\u7edf\u8ba1\u3002type=0 and channel!=1 and   channel !=1010000001 and order_status\u53d8\u4e3a6\u3002\u6570\u636e\u6e90\uff1ag_order_a"
            },
            {
               "name":"\u5b9e\u65f6\u8ba2\u5355\u5e94\u7b54\u540e\u53d6\u6d88\u91cf",
               "id":"monitor_zhuanche_realtime_order_after_deal_cancel_num",
               "title":"\u6309\u7167\u8ba2\u5355\u53d6\u6d88\u65f6\u95f4\u7edf\u8ba1\u3002type=0 and channel!=1 and   channel !=1010000001 and order_status\u53d8\u4e3a7\u3002\u6570\u636e\u6e90\uff1ag_order_a"
            },
            {
               "name":"\u5b9e\u65f6\u8ba2\u5355\u6210\u4ea4\u7387",
               "id":"monitor_zhuanche_realtime_order_deal_rate",
               "title":"\u6309\u7167\u8ba2\u5355\u547c\u53eb\u65f6\u95f4\u7edf\u8ba1\uff0c\u6210\u4ea4\u91cf\/\u547c\u53eb\u91cf\u3002\u5b9a\u4e49\u89c2\u5bdf\u65f6\u523b\u4e3as\u3002\u65f6\u523bs\u7684\u5b9e\u65f6\u76d1\u63a7\u7684\u6210\u4ea4\u7387\u5b9a\u4e49\u662f s\u5206\u949f\u5185\u547c\u53eb\u5230\u5f53\u524d\u65f6\u95f4\u5b8c\u6210\u7684\u8ba2\u5355\u6570 \/ s\u5206\u949f\u5185\u547c\u53eb\u8ba2\u5355\u6570\u3002",
               "warn":0
            },
            {
               "name":"\u5b9e\u65f6\u8ba2\u5355\u5e94\u7b54\u7387",
               "id":"monitor_zhuanche_realtime_order_answer_rate",
               "title":"\u65f6\u523bs\u7684\u5e94\u7b54\u7387 = \u65f6\u523bs\u5206\u949f\u547c\u53eb\u7684\u5230\u5f53\u524d\u65f6\u523b\u88ab\u5e94\u7b54\u6570 \/ \u65f6\u523bs\u5206\u949f\u547c\u53eb\u8ba2\u5355\u6570\u3002\u5982\u679c\u65f6\u523bs\u548c\u5f53\u524d\u65f6\u523b\u63a5\u8fd1\u7684\u8bdd\uff0c\u5b9e\u65f6\u5e94\u7b54\u7387\u5c31\u53ef\u80fd\u504f\u4f4e\u3002",
               "warn":0
            },
            {
               "name":"\u5b9e\u65f6\u8ba2\u5355\u5e94\u7b54\u91cf",
               "id":"monitor_zhuanche_realtime_order_answer_num",
               "title":"type=0 && channel !=1 && channel !=1010000001 && order_status\u53d8\u4e3a1\u3002\u6570\u636e\u6e90:g_order_create_time"
            },
            {
               "name":"\u5b9e\u65f6\u8ba2\u5355\u5e73\u5747\u5e94\u7b54\u8ddd\u79bb",
               "id":"monitor_zhuanche_realtime_order_deal_distance",
               "title":"\u6210\u4ea4\u603b\u8ddd\u79bb\/\u6210\u4ea4\u91cf",
               "warn":0
            },
            {
               "name":"\u5b9e\u65f6\u8ba2\u5355\u64ad\u5355\u91cf",
               "id":"monitor_zhuanche_realtime_order_broadcast_num",
               "title":"\u6309\u7167\u64ad\u5355\u65f6\u95f4\u7edf\u8ba1.type=0.\u6570\u636e\u6e90\uff1aflume_g_orderbroadcast"
            },
            {
               "name":"\u5b9e\u65f6\u8ba2\u5355\u62a2\u5355\u91cf",
               "id":"monitor_zhuanche_realtime_order_competting_num",
               "title":"\u6309\u7167\u62a2\u5355\u65f6\u95f4\u7edf\u8ba1.type=0.\u6570\u636e\u6e90\uff1aflume_g_new_strive_broadcast"
            },
            {
               "name":"\u5b9e\u65f6\u8ba2\u5355\u542c\u5355\u62a2\u5355\u7387",
               "id":"monitor_zhuanche_realtime_order_tingdan_rate",
               "title":"\u62a2\u5355\u91cf\/\u64ad\u5355\u91cf \uff08\u7edf\u8ba1\u65f6\u95f4\u4e0d\u4e00\u81f4\uff09",
               "warn":0
            },
            {
               "name":"\u5b9e\u65f6\u8ba2\u5355STR",
               "id":"monitor_zhuanche_realtime_order_str",
               "title":"\u8ba2\u5355STR\/\u64ad\u5355\u91cf\uff08\u7edf\u8ba1\u65f6\u95f4\u4e0d\u4e00\u81f4 \u524d\u8005\u662f\u6309STR\u8ba1\u7b97\u65f6\u95f4\uff0c\u540e\u8005\u662f\u6309\u64ad\u5355\u65f6\u95f4\uff09"
            }
         ]
      },
      {
         "name":"\u9884\u7ea6\u8ba2\u5355",
         "items":[
            {
               "name":"\u9884\u7ea6\u8ba2\u5355\u547c\u53eb\u91cf",
               "id":"monitor_zhuanche_reservation_order_call_num",
               "title":"\u6309\u7167\u8ba2\u5355\u547c\u53eb\u65f6\u95f4\u7edf\u8ba1\u3002\u5f53\u524d\u63d2\u5165\u8ba2\u5355\u3002type=1 and channel!=1 and   channel !=1010000001\u3002\u6570\u636e\u6e90\uff1ag_order_a"
            },
            {
               "name":"\u9884\u7ea6\u8ba2\u5355\u6210\u4ea4\u91cf",
               "id":"monitor_zhuanche_reservation_order_deal_num",
               "title":"\u6309\u7167\u8ba2\u5355\u547c\u53eb\u65f6\u95f4\u7edf\u8ba1\u3002type=1 and channel!=1 and   channel !=1010000001 and order_status\u53d8\u4e3a5\u3002\u6570\u636e\u6e90\uff1ag_order_a"
            },
            {
               "name":"\u9884\u7ea6\u8ba2\u5355\u5e94\u7b54\u524d\u53d6\u6d88\u91cf",
               "id":"monitor_zhuanche_reservation_order_before_deal_cancel_num",
               "title":"\u6309\u7167\u8ba2\u5355\u53d6\u6d88\u65f6\u95f4\u7edf\u8ba1\u3002type=1 and channel!=1 and   channel !=1010000001 and order_status\u53d8\u4e3a6\u3002\u6570\u636e\u6e90\uff1ag_order_a"
            },
            {
               "name":"\u9884\u7ea6\u8ba2\u5355\u5e94\u7b54\u540e\u53d6\u6d88\u91cf",
               "id":"monitor_zhuanche_reservation_order_after_deal_cancel_num",
               "title":"\u6309\u7167\u8ba2\u5355\u53d6\u6d88\u65f6\u95f4\u7edf\u8ba1\u3002type=1 and channel!=1 and   channel !=1010000001 and order_status=7"
            },
            {
               "name":"\u9884\u7ea6\u8ba2\u5355\u5e94\u7b54\u7387",
               "id":"monitor_zhuanche_reservation_order_deal_rate",
               "title":"\u6309\u7167\u8ba2\u5355\u547c\u53eb\u65f6\u95f4\u7edf\u8ba1\uff0c\u6210\u4ea4\u91cf\/\u547c\u53eb\u91cf",
               "warn":0
            },
            {
               "name":"\u9884\u7ea6\u8ba2\u5355\u64ad\u5355\u91cf",
               "id":"monitor_zhuanche_reservation_order_broadcast_num",
               "title":"\u6309\u7167\u64ad\u5355\u65f6\u95f4\u7edf\u8ba1\u3002type=1,\u6570\u636e\u6e90\uff1aflume_g_orderbroadcast"
            },
            {
               "name":"\u9884\u7ea6\u8ba2\u5355\u62a2\u5355\u91cf",
               "id":"monitor_zhuanche_reservation_order_competting_num",
               "title":"\u6309\u7167\u62a2\u5355\u65f6\u95f4\u7edf\u8ba1\u3002order_type=1.\u6570\u636e\u6e90\uff1aflume_g_new_strive_broadcast"
            },
            {
               "name":"\u9884\u7ea6\u8ba2\u5355\u542c\u5355\u62a2\u5355\u7387",
               "id":"monitor_zhuanche_reservation_order_tingdan_rate",
               "title":"\u62a2\u5355\u91cf\/\u64ad\u5355\u91cf \uff08\u7edf\u8ba1\u65f6\u95f4\u4e0d\u4e00\u81f4\uff09",
               "warn":0
            }
         ]
      },
      {
         "name":"\u53f8\u673a\u5728\u7ebf",
         "items":[
            {
               "name":"\u7a7a\u95f2\u53f8\u673a\u5728\u7ebf\u6570",
               "id":"monitor_zhuanche_driver_online_free_num",
               "title":""
            },
            {
               "name":"\u670d\u52a1\u4e2d\u53f8\u673a\u5728\u7ebf\u6570",
               "id":"monitor_zhuanche_driver_online_service_num",
               "title":""
            },
            {
               "name":"\u603b\u53f8\u673a\u5728\u7ebf\u6570",
               "id":"monitor_zhuanche_driver_online_total_num",
               "title":""
            },
            {
               "name":"\u670d\u52a1\u53f8\u673a\u6bd4\u4f8b",
               "id":"monitor_zhuanche_driver_online_service_rate",
               "title":"",
               "warn":0
            }
         ]
      },
      {
         "name":"\u5fae\u4fe1\u63d0\u73b0",
         "items":[
            {
               "name":"\u5fae\u4fe1\u63d0\u73b0\u53d1\u8d77\u6570",
               "id":"monitor_zhuanche_weixin_withdraw_start_num",
               "title":"\u6309\u63d0\u73b0\u65f6\u95f4\u7edf\u8ba1\u3002\u5f53\u524d\u63d2\u5165\u3002\u6570\u636e\u6e90\uff1au_withdraw_bill"
            },
            {
               "name":"\u5fae\u4fe1\u63d0\u73b0\u53d1\u8d77\u91d1\u989d",
               "id":"monitor_zhuanche_weixin_withdraw_start_money",
               "title":"\u6309\u63d0\u73b0\u65f6\u95f4\u7edf\u8ba1\u3002\u5f53\u524d\u63d2\u5165\u3002\u6570\u636e\u6e90\uff1au_withdraw_bill"
            },
            {
               "name":"\u5fae\u4fe1\u63d0\u73b0\u6210\u529f\u6570",
               "id":"monitor_zhuanche_weixin_withdraw_succ_num",
               "title":"\u6309\u63d0\u73b0\u65f6\u95f4\u7edf\u8ba1\u3002status\u53d8\u4e3a1\u3002\u6570\u636e\u6e90\uff1au_withdraw_bill"
            },
            {
               "name":"\u5fae\u4fe1\u63d0\u73b0\u6210\u529f\u91d1\u989d",
               "id":"monitor_zhuanche_weixin_withdraw_succ_money",
               "title":"\u6309\u63d0\u73b0\u65f6\u95f4\u7edf\u8ba1\u3002status\u53d8\u4e3a1\u3002\u6570\u636e\u6e90\uff1au_withdraw_bill"
            }
         ]
      },
      {
         "name":"\u8d85\u7ea7\u4efb\u52a1",
         "items":[
            {
               "name":"\u4efb\u52a1\u53d1\u8d77\u6570",
               "id":"monitor_zhuanche_task_start_num",
               "title":"\u6309\u4efb\u52a1\u53d1\u8d77\u65f6\u95f4\u7edf\u8ba1\u3002channel!=1 and channel!=1010000001\u3002datasource=g_raptor_rank"
            },
            {
               "name":"\u53c2\u4e0e\u4efb\u52a1\u53f8\u673a\u6570",
               "id":"monitor_zhuanche_task_participate_driver_num",
               "title":"\u6309\u4efb\u52a1\u53d1\u8d77\u65f6\u95f4\u7edf\u8ba1\u3002channel!=1 and channel!=1010000001\u3002datasource=g_raptor_rank"
            },
            {
               "name":"\u5956\u52b1\u603b\u91d1\u989d",
               "id":"monitor_zhuanche_task_awards_total_money",
               "title":"\u6309\u5956\u52b1\u65f6\u95f4\u7edf\u8ba1\u3002channel!=1 and channel!=1010000001\u3002datasource=g_raptor_rank"
            }
         ]
      },
      {
         "name":"\u5206\u4eab\u7cfb\u7edf",
         "items":[
            {
               "name":"\u652f\u4ed8\u540e\u521b\u5efa\u5206\u4eab\u6570",
               "id":"monitor_zhuanche_pay_share_hongbao_num",
               "title":"\u6309\u5206\u4eab\u65f6\u95f4\u7edf\u8ba1\u3002\u5f53\u524d\u63d2\u5165\u3002\u6570\u636e\u6e90\uff1ashare_info\u3002"
            },
            {
               "name":"\u9886\u53d6\u5c0f\u7ea2\u5305\u6570",
               "id":"monitor_zhuanche_hongbao_receive_num",
               "title":"\u6309\u9886\u53d6\u65f6\u95f4\u7edf\u8ba1\u3002\u5f53\u524d\u63d2\u5165\u3002\u6570\u636e\u6e90\uff1ashare_part"
            },
            {
               "name":"\u9886\u53d6\u5c0f\u7ea2\u5305\u91d1\u989d",
               "id":"monitor_zhuanche_hongbao_receive_money",
               "title":"\u6309\u9886\u53d6\u65f6\u95f4\u7edf\u8ba1\u3002\u5f53\u524d\u63d2\u5165\u3002\u6570\u636e\u6e90\uff1ashare_part"
            }
         ]
      },
      {
         "name":"\u6307\u6d3e\u6a21\u5f0f",
         "items":[
            {
               "name":"\u62a2\u5355\u6a21\u5f0f\u64ad\u5355\u6570",
               "id":"monitor_zhuanche_zhipai_qmode_broadcast_num",
               "title":"\u6309\u64ad\u5355\u65f6\u95f4\u7edf\u8ba1\u3002is_zhipai_driver=1 && type=0 && zhipai_stat%2 != 1 \u6570\u636e\u6e90\u4e3aflume_g_orderbroadcast"
            },
            {
               "name":"\u6307\u6d3e\u6a21\u5f0f\u64ad\u5355\u6570",
               "id":"monitor_zhuanche_zhipai_amode_broadcast_num",
               "title":"\u6309\u64ad\u5355\u65f6\u95f4\u7edf\u8ba1\u3002is_zhipai_driver=1 && type=0 && zhipai_stat%2 = 1 \u6570\u636e\u6e90\u4e3aflume_g_orderbroadcast"
            },
            {
               "name":"\u62a2\u5355\u6a21\u5f0f\u8ba2\u5355\u6570",
               "id":"monitor_zhuanche_zhipai_qmode_order_num",
               "title":"\u6309\u64ad\u5355\u65f6\u95f4\u7edf\u8ba1\u3002is_zhipai_driver=0 && type=0 && zhipai_stat%2 != 1 \u6570\u636e\u6e90\u4e3aflume_g_orderbroadcast"
            },
            {
               "name":"\u6307\u6d3e\u6a21\u5f0f\u8ba2\u5355\u6570",
               "id":"monitor_zhuanche_zhipai_amode_order_num",
               "title":"\u6309\u64ad\u5355\u65f6\u95f4\u7edf\u8ba1\u3002is_zhipai_driver=1 && type=0 && zhipai_stat%2 = 1 \u6570\u636e\u6e90\u4e3aflume_g_orderbroadcast"
            }
         ]
      },
      {
         "name":"\u52a8\u6001\u8c03\u4ef7",
         "items":[
            {
               "name":"\u603b\u5192\u6ce1\u6570",
               "id":"monitor_zhuanche_dynamic_price_total_request",
               "title":""
            },
            {
               "name":"\u8c03\u4ef7\u5192\u6ce1\u6570",
               "id":"monitor_zhuanche_dynamic_price_b",
               "title":""
            },
            {
               "name":"\u8c03\u4ef7\u53d1\u5355\u6570",
               "id":"monitor_zhuanche_dynamic_price_e",
               "title":""
            },
            {
               "name":"\u672a\u8c03\u4ef7\u5192\u6ce1\u6570",
               "id":"monitor_zhuanche_no_dynamic_price_mp",
               "title":""
            },
            {
               "name":"\u672a\u8c03\u4ef7\u53d1\u5355\u6570",
               "id":"monitor_zhuanche_no_dynamic_price_fd",
               "title":""
            },
            {
               "name":"\u8c03\u4ef7\u6bd4\u4f8b",
               "id":"monitor_zhuanche_dynamic_price_tiaojia_rate",
               "title":"",
               "warn":0
            },
            {
               "name":"\u8c03\u4ef7\u63a5\u53d7\u7387",
               "id":"monitor_zhuanche_dynamic_price_tiaojia_accept_rate",
               "title":"",
               "warn":0
            },
            {
               "name":"\u672a\u8c03\u4ef7\u63a5\u53d7\u7387",
               "id":"monitor_zhuanche_dynamic_price_notiaojia_accept_rate",
               "title":"",
               "warn":0
            },
            {
               "name":"\u8c03\u4ef7\u6210\u4ea4\u7387",
               "id":"monitor_zhuanche_dynamic_price_tiaojia_deal_rate",
               "title":"",
               "warn":0
            }
         ]
      },
      {
         "name":"B2B\u652f\u4ed8",
         "items":[
            {
               "name":"B2B\u652f\u4ed8\u53d1\u8d77\u6570",
               "id":"monitor_zhuanche_b2b_pay_start_num",
               "title":"\u6309\u652f\u4ed8\u65f6\u95f4\u7edf\u8ba1\u3002\u5f53\u524d\u63d2\u5165channel=11001\uff0c\u6570\u636e\u6e90d_didibill_part"
            },
            {
               "name":"B2B\u652f\u4ed8\u6210\u529f\u6570",
               "id":"monitor_zhuanche_b2b_pay_succ_num",
               "title":"\u6309\u652f\u4ed8\u65f6\u95f4\u7edf\u8ba1\u3002channel=11001 and status\u53d8\u4e3a3\uff0c\u6570\u636e\u6e90d_didibill_part"
            },
            {
               "name":"B2B\u652f\u4ed8\u6210\u529f\u91d1\u989d",
               "id":"monitor_zhuanche_b2b_pay_succ_money",
               "title":"\u6309\u652f\u4ed8\u65f6\u95f4\u7edf\u8ba1\u3002channel=11001 and status\u53d8\u4e3a3\uff0c\u6570\u636e\u6e90d_didibill_part"
            }
         ]
      },
      {
         "name":"\u4e13\u8f66\u652f\u4ed8",
         "items":[
            {
               "name":"\u652f\u4ed8\u53d1\u8d77\u91cf",
               "id":"monitor_zhuanche_pay_start_num",
               "title":"\u6309\u652f\u4ed8\u65f6\u95f4\u7edf\u8ba1\u3002\n\u5f53\u524d\u63d2\u5165channel in(124,126,127,110,122,128,129,130,137)\u3002\u6570\u636e\u6e90\u4e3ad_didibill_part"
            },
            {
               "name":"\u652f\u4ed8\u6210\u529f\u91cf",
               "id":"monitor_zhuanche_pay_succ_num",
               "title":"\u6309\u652f\u4ed8\u65f6\u95f4\u7edf\u8ba1\u3002\nchannel in(124,126,127,110,122,128,129,130,137) and status\u53d8\u4e3a3\u3002\u6570\u636e\u6e90\u4e3ad_didibill_part"
            },
            {
               "name":"\u652f\u4ed8\u6210\u529f\u91d1\u989d",
               "id":"monitor_zhuanche_pay_succ_money",
               "title":"\u6309\u652f\u4ed8\u65f6\u95f4\u7edf\u8ba1\u3002\nchannel in(124,126,127,110,122,128,129,130,137) and status\u53d8\u4e3a3\u3002\u6570\u636e\u6e90\u4e3ad_didibill_part"
            },
            {
               "name":"\u652f\u4ed8\u56de\u8c03\u53d1\u8d77\u6570",
               "id":"monitor_zhuanche_pay_callback_start_num",
               "title":"\u6309\u652f\u4ed8\u56de\u8c03\u65f6\u95f4\u7edf\u8ba1\u3002\u6570\u636e\u6e90\uff1amonitor_d_weixin_pay"
            },
            {
               "name":"\u652f\u4ed8\u56de\u8c03\u5ef6\u8fdf\u6570",
               "id":"monitor_zhuanche_pay_callback_delay_num",
               "title":"\u56de\u8c03\u6210\u529f\u65f6\u95f4\u6216\u5f53\u671f\u7edf\u8ba1\u65f6\u95f4 - \u652f\u4ed8\u53d1\u8d77\u65f6\u95f4>60\u79d2\u3002\u6570\u636e\u6e90\uff1amonitor_d_weixin_pay",
               "warn":0
            },
            {
               "name":"\u652f\u4ed8\u56de\u8c03\u5ef6\u8fdf\u7387",
               "id":"monitor_zhuanche_pay_callback_delay_rate",
               "title":"\u5ef6\u8fdf\u6570\/\u53d1\u8d77\u6570",
               "warn":0
            }
         ]
      },
      {
         "name":"\u8ba1\u4ef7\u7cfb\u7edf",
         "items":[
            {
               "name":"\u9884\u4f30\u4ef7\u548c\u5b9e\u65f6\u8ba1\u4ef7\u6bd4\u503c\u7684\u5747\u503c",
               "id":"monitor_zhuanche_jijia_yugu_avg"
            },
            {
               "name":"\u9884\u4f30\u4ef7\u548c\u6210\u4ea4\u4ef7\u5dee\u522b\u5927\u4e8e5%\u7684\u8ba2\u5355\u6570\u91cf",
               "id":"monitor_zhuanche_jijia_5_num",
               "title":"beyond_5=1 \u3002\u6570\u636e\u6e90\uff1aGS_PRICE_API_TOPIC_g_f_pre_compare_fee"
            },
            {
               "name":"\u9884\u4f30\u4ef7\u548c\u6210\u4ea4\u4ef7\u5dee\u522b\u5927\u4e8e5%\u7684\u8ba2\u5355\u6bd4\u4f8b",
               "id":"monitor_zhuanche_jijia_5_rate",
               "warn":0
            },
            {
               "name":"\u9884\u4f30\u4ef7\u548c\u6210\u4ea4\u4ef7\u5dee\u522b\u5927\u4e8e20%\u7684\u8ba2\u5355\u6570\u91cf",
               "id":"monitor_zhuanche_jijia_20_num",
               "title":"beyond_20=1 \u3002\u6570\u636e\u6e90\uff1aGS_PRICE_API_TOPIC_g_f_pre_compare_fee"
            },
            {
               "name":"\u9884\u4f30\u4ef7\u548c\u6210\u4ea4\u4ef7\u5dee\u522b\u5927\u4e8e20%\u7684\u8ba2\u5355\u6bd4\u4f8b",
               "id":"monitor_zhuanche_jijia_20_rate",
               "warn":0
            },
            {
               "name":"\u9884\u4f30\u4ef7\u548c\u6210\u4ea4\u4ef7\u5dee\u522b\u5927\u4e8e50%\u7684\u8ba2\u5355\u6570\u91cf",
               "id":"monitor_zhuanche_jijia_50_num",
               "title":"beyond_50=1 \u3002\u6570\u636e\u6e90\uff1aGS_PRICE_API_TOPIC_g_f_pre_compare_fee"
            },
            {
               "name":"\u9884\u4f30\u4ef7\u548c\u6210\u4ea4\u4ef7\u5dee\u522b\u5927\u4e8e50%\u7684\u8ba2\u5355\u6bd4\u4f8b",
               "id":"monitor_zhuanche_jijia_50_rate",
               "warn":0
            }
         ]
      },
      {
         "name":"\u6e20\u9053\u793c\u5305",
         "items":[
            {
               "name":"\u5927\u7ea2\u5305\u9886\u53d6\u91cf",
               "id":"monitor_zhuanche_channal_package_big_num",
               "title":"\u6309\u9886\u53d6\u65f6\u95f4\u7edf\u8ba1\u3002\u5f53\u524d\u63d2\u5165\u3002\u6570\u636e\u6e90\uff1aa_channel_package"
            },
            {
               "name":"\u5c0f\u7ea2\u5305\u9886\u53d6\u91cf",
               "id":"monitor_zhuanche_channal_package_small_num",
               "title":"\u6309\u9886\u53d6\u65f6\u95f4\u7edf\u8ba1\u3002\u5f53\u524d\u63d2\u5165\u3002\u6570\u636e\u6e90\uff1aa_channel_gift"
            },
            {
               "name":"\u5c0f\u7ea2\u5305\u7ed1\u5b9a\u5931\u8d25\u91cf",
               "id":"monitor_zhuanche_channal_package_small_fail_num",
               "title":"\u6309\u786e\u8ba4\u5931\u8d25\u65f6\u95f4\u7edf\u8ba1\u3002status\u53d8\u4e3a2\u3002\u6570\u636e\u6e90\uff1aa_channel_gift"
            }
         ]
      },
      {
         "name":"\u62fc\u8f66",
         "items":[
            {
               "name":"\u5b9e\u65f6\u62fc\u8f66\u5355\u547c\u53eb\u91cf",
               "id":"monitor_pinche_realtime_order_call_num",
               "title":"combo_type=4 && metric_key=g_order_create\u3002\u6570\u636e\u6e90\uff1aflume_gulfstream_api_log"
            },
            {
               "name":"\u5b9e\u65f6\u613f\u62fc\u7387",
               "id":"monitor_pinche_realtime_order_yuanpin_rate",
               "title":"\u5b9e\u65f6\u62fc\u8f66\u5355\u547c\u53eb\u91cf\/\u5b9e\u65f6\u603b\u547c\u53eb\u91cf",
               "warn":0
            },
            {
               "name":"\u5b9e\u65f6\u62fc\u8f66\u5355\u5e94\u7b54\u91cf",
               "id":"monitor_pinche_realtime_order_answer_num",
               "title":"combo_type=4 && metric_key=g_new_strive_suc\u3002\u6570\u636e\u6e90\uff1aflume_gulfstream_api_log"
            },
            {
               "name":"\u5b9e\u65f6\u62fc\u8f66\u5355\u5e94\u7b54\u7387",
               "id":"monitor_pinche_realtime_order_answer_rate",
               "title":"\u5b9e\u65f6\u62fc\u8f66\u5355\u5e94\u7b54\u91cf\/\u5b9e\u65f6\u62fc\u8f66\u5355\u547c\u53eb\u91cf",
               "warn":0
            },
            {
               "name":"\u62fc\u8f66\u5355\u7b2c\u4e00\u5355\u64ad\u5355\u91cf",
               "id":"monitor_pinche_realtime_order_first_broadcast_num",
               "title":"status=1 && ordershare=1 \u3002\u6570\u636e\u6e90\u4e3aflume_g_orderbroadcast"
            },
            {
               "name":"\u62fc\u8f66\u5355\u7b2c\u4e8c\u5355\u64ad\u5355\u91cf",
               "id":"monitor_pinche_realtime_order_second_broadcast_num",
               "title":"status=15 && ordershare=1 \u3002\u6570\u636e\u6e90\u4e3aflume_g_orderbroadcast"
            },
            {
               "name":"\u62fc\u8f66\u5355\u7b2c\u4e00\u5355\u542c\u62a2\u7387",
               "id":"monitor_pinche_realtime_order_first_strive_rate",
               "title":"\u7b2c\u4e00\u5355\u62a2\u5355\u91cf\/\u7b2c\u4e00\u5355\u64ad\u5355\u91cf",
               "warn":0
            },
            {
               "name":"\u62fc\u8f66\u5355\u7b2c\u4e8c\u5355\u542c\u62a2\u7387",
               "id":"monitor_pinche_realtime_order_second_strive_rate",
               "title":"\u7b2c\u4e8c\u5355\u62a2\u5355\u91cf\/\u7b2c\u4e8c\u5355\u64ad\u5355\u91cf",
               "warn":0
            },
            {
               "name":"\u62fc\u8f66\u5355\u5e94\u7b54\u524d\u53d6\u6d88\u91cf",
               "id":"monitor_pinche_realtime_order_before_answer_cancle_num",
               "title":"combo_type=4 && metric_key=g_cancel_order\u3002\u6570\u636e\u6e90\uff1aflume_gulfstream_api_log"
            },
            {
               "name":"\u62fc\u8f66\u5355\u5e94\u7b54\u540e\u53d6\u6d88\u91cf",
               "id":"monitor_pinche_realtime_order_after_answer_cancle_num",
               "title":"combo_type=4 && metric_key=g_cancel_trip\u3002\u6570\u636e\u6e90\uff1aflume_gulfstream_api_log"
            },
            {
               "name":"\u62fc\u8f66\u5355\u6210\u4ea4\u91cf",
               "id":"monitor_pinche_realtime_order_succ_num",
               "title":"combo_type=4 && metric_key=g_finish_order\u3002\u6570\u636e\u6e90\uff1aflume_gulfstream_api_log"
            },
            {
               "name":"\u8f7d\u4eba\u8f66\u6210\u4ea4\u8ba2\u5355\u91cf",
               "id":"monitor_pinche_realtime_order_zairen_succ_num",
               "title":"combo_type=4 && metric_key=g_new_strive_suc && sequence=0\u3002\u6570\u636e\u6e90\uff1aflume_gulfstream_api_log"
            },
            {
               "name":"\u7b2c\u4e00\u5355\u5e73\u5747\u6210\u4ea4\u8ddd\u79bb",
               "id":"monitor_pinche_realtime_order_first_avg_distance",
               "title":"\u7b2c\u4e00\u5355\u603b\u8ddd\u79bb\/\u62fc\u8f66\u5355\u7b2c\u4e00\u5355\u62a2\u5355\u91cf",
               "warn":0
            },
            {
               "name":"\u7b2c\u4e8c\u5355\u5e73\u5747\u6210\u4ea4\u8ddd\u79bb",
               "id":"monitor_pinche_realtime_order_second_avg_distance",
               "title":"\u7b2c\u4e8c\u5355\u603b\u8ddd\u79bb\/\u62fc\u8f66\u5355\u7b2c\u4e8c\u5355\u62a2\u5355\u91cf",
               "warn":0
            },
            {
               "name":"\u63a5\u7b2c\u4e00\u5355\u62fc\u8f66\u5355\u53f8\u673a\u6570",
               "id":"monitor_pinche_driver_first_accept_num",
               "title":"combo_type=4 && metric_key=g_new_strive_suc && sequence=1\u3002\u6570\u636e\u6e90\uff1aflume_gulfstream_api_log"
            },
            {
               "name":"\u62fc\u6210\u53f8\u673a\u6570\uff08\u63a5\u7b2c\u4e8c\u5355\u62fc\u8f66\u5355\u7684\u53f8\u673a\uff09",
               "id":"monitor_pinche_driver_second_accept_num",
               "title":"combo_type=4 && metric_key=g_new_strive_suc && sequence=0\u3002\u6570\u636e\u6e90\uff1aflume_gulfstream_api_log"
            },
            {
               "name":"\u52a8\u6001\u6298\u6263\u8fd4\u56de\u91cf",
               "id":"monitor_pinche_zhekou_return_num",
               "title":"combo_type=4 && metric_key=g_feature_dynamic_price\u3002\u6570\u636e\u6e90\uff1am2_zc_dynamic_price_public_fmt"
            },
            {
               "name":"\u52a8\u6001\u6298\u6263\u5e73\u5747\u503c",
               "id":"monitor_pinche_zhekou_avg",
               "title":"combo_type=4 && metric_key=g_feature_dynamic_price\u65e5\u5fd7\u4e2d\u5bf9\u5e94\u7684dynamic_discount \u5747\u503c\u3002\u6570\u636e\u6e90\uff1am2_zc_dynamic_price_public_fmt"
            }
         ]
      }
   ],
   "kefu_items":[
      {
         "name":"\u5ba2\u670d\u76d1\u63a7",
         "items":[
            {
               "name":"\u8fdb\u7ebf\u91cf",
               "id":"cs_call_analysis_cnt",
               "title":"\u4ece\u7f13\u5b58\u4e2d\u83b7\u53d6"
            },
            {
               "name":"\u63a5\u8d77\u91cf",
               "id":"cs_call_analysis_succcnt",
               "title":"\u4ece\u7f13\u5b58\u4e2d\u83b7\u53d6"
            },
            {
               "name":"\u63a5\u8d77\u7387",
               "id":"cs_call_analysis_succrate",
               "title":"\u4ece\u7f13\u5b58\u4e2d\u83b7\u53d6",
               "warn":0
            }
         ]
      }
   ]
}